arxa/__init__.py
arxa/arxiv_utils.py
arxa/cli.py
arxa/config.py
arxa/llm_backends.py
arxa/pdf_utils.py
arxa/prompts.py
arxa/repo_utils.py
arxa/research_review.py
arxa/server.py
arxa-0.1.13.dist-info/METADATA
arxa-0.1.13.dist-info/WHEEL
arxa-0.1.13.dist-info/entry_points.txt
arxa-0.1.13.dist-info/top_level.txt
arxa-0.1.13.dist-info/RECORD
