Metadata-Version: 2.2
Name: arxa
Version: 0.1.13
Summary: A research automation tool for fetching, summarizing, and enhancing arXiv papers.
Home-page: https://github.com/binaryninja/arxa
Author: Jeremy Richards
Author-email: jeremy@richards.ai
Classifier: Programming Language :: Python :: 3
Requires-Dist: PyPDF2
Requires-Dist: arxiv
Requires-Dist: anthropic
Requires-Dist: ollama
Requires-Dist: openai
Requires-Dist: requests
Requires-Dist: tenacity
Requires-Dist: tqdm
Requires-Dist: aiohttp
Requires-Dist: pyyaml
Requires-Dist: tiktoken
Requires-Dist: httpx<1,>=0.23.0
Requires-Dist: rich
Dynamic: author
Dynamic: author-email
Dynamic: classifier
Dynamic: description
Dynamic: description-content-type
Dynamic: home-page
Dynamic: requires-dist
Dynamic: summary
